[
    {
        "title": "4725F10701 - Prognosem\u00f6glichkeiten f\u00fcr naturbedingte Einwirkungen von Au\u00dfen (EVA) mit k\u00fcnstlicher Intelligenz auf Endlager in der Betriebsphase (PEAK)",
        "link": "https://www.evergabe-online.de/tenderdetails.html?id=796615"
    },
    {
        "title": "4724F90201 - M\u00f6glichkeiten der Markierung eines geologischen Endlagers in der Bundesrepublik Deutschland (MarkEnd)",
        "link": "https://www.evergabe-online.de/tenderdetails.html?id=796610"
    },
    {
        "title": "Fliesenarbeiten - Tr\u00dcbPl Altengrabow, Instandsetzung Innentreppen Geb. 335/336 (NMB 427-25)",
        "link": "https://www.evergabe-online.de/tenderdetails.html?id=796588"
    },
    {
        "title": "Metallbauarbeiten - Tr\u00dcbPl Altengrabow, Instandsetzung Innentreppen Geb. 335/336 (NMB 428-25)",
        "link": "https://www.evergabe-online.de/tenderdetails.html?id=796585"
    },
    {
        "title": "Kampfmittelsondierung auf Wasser und an Land im Liegehafen Pinnengraben Warnem\u00fcnde",
        "link": "https://www.evergabe-online.de/tenderdetails.html?id=796287"
    },
    {
        "title": "Lamellen Agentur Erfurt",
        "link": "https://www.evergabe-online.de/tenderdetails.html?id=796577"
    },
    {
        "title": "R\u00fcckbau von 25 Bauwerken - ehem. Kaserne Cracau, R\u00fcckbau u. Beseitigung von Abfallablagerungen (NMB 450-25)",
        "link": "https://www.evergabe-online.de/tenderdetails.html?id=796570"
    },
    {
        "title": "FKZ 3724 15 703 0 - Skalierung von Prozessen zur F\u00f6rderung der Umverteilung urbaner Verkehrsfl\u00e4chen",
        "link": "https://www.evergabe-online.de/tenderdetails.html?id=796563"
    },
    {
        "title": "Umzugsdienstleistungen BVA Rostock",
        "link": "https://www.evergabe-online.de/tenderdetails.html?id=796568"
    },
    {
        "title": "Gestellung von Gefahrstoffbeh\u00e4ltern, Abholung, Transport und ordnungsgem\u00e4\u00dfe Entsorgung von Schadstoffhaltigen Abf\u00e4llen von 3 Wertstoffh\u00f6fen im BLK 2026",
        "link": "https://www.evergabe-online.de/tenderdetails.html?id=795721"
    }
]