[
    {
        "title": "FKZ 3726 51 206 0 - Untersuchung luftgetragener PFAS-Emission, -Immission und -Deposition",
        "link": "https://www.evergabe-online.de/tenderdetails.html?id=860423"
    },
    {
        "title": "Erstbeschaffung mobile Gasmesstechnik MZS \"Scharh\u00f6rn\"",
        "link": "https://www.evergabe-online.de/tenderdetails.html?id=860392"
    },
    {
        "title": "Tief- und Stra\u00dfenbauleistungen",
        "link": "https://www.evergabe-online.de/tenderdetails.html?id=860386"
    },
    {
        "title": "Regalsystem",
        "link": "https://www.evergabe-online.de/tenderdetails.html?id=860418"
    },
    {
        "title": "Lektorat, Korrektorat und Satz der Fachhefte",
        "link": "https://www.evergabe-online.de/tenderdetails.html?id=860279"
    },
    {
        "title": "KBS Campus, hier: Rohrrahment\u00fcren",
        "link": "https://www.evergabe-online.de/tenderdetails.html?id=860270"
    },
    {
        "title": "Herstellung, Lieferung und Montage von zwei neuen Schneckengetrieben, Wehranlage Gundelsheim, \u00d6ffnung II",
        "link": "https://www.evergabe-online.de/tenderdetails.html?id=859896"
    },
    {
        "title": "Mahd an Gew\u00e4sser, TO 15 - Mittelgraben",
        "link": "https://www.evergabe-online.de/tenderdetails.html?id=860395"
    },
    {
        "title": "Regionaldirektion Chemnitz, Instandsetzung der Rettungszeichenleuchten, Niederspannungsinstallationsanlagen/ Sicherheitsbeleuchtung",
        "link": "https://www.evergabe-online.de/tenderdetails.html?id=860399"
    },
    {
        "title": "Aufforstungsma\u00dfnahmen im Bundesforstbetrieb Vorpommern-Strelitz, Reviere Bannenbr\u00fcck, Bellin und Glash\u00fctte (Vergabenummer VOEK 163-26)",
        "link": "https://www.evergabe-online.de/tenderdetails.html?id=859639"
    }
]