[
    {
        "title": "Influencer Marketing & Event Agentur 2026",
        "link": "https://www.evergabe-online.de/tenderdetails.html?id=852416"
    },
    {
        "title": "11-0498 Arnstadt, Prof.-Frosch-Str. 46a - Instandsetzung Laubeng\u00e4nge und Fassade, Los 3 Dacharbeiten Flachdach und Laubeng\u00e4nge",
        "link": "https://www.evergabe-online.de/tenderdetails.html?id=852355"
    },
    {
        "title": "11-0498 Arnstadt, Prof.-Frosch-Str. 46a - Instandsetzung Laubeng\u00e4nge und Fassade, Los 2 Putzarbeiten Fassade",
        "link": "https://www.evergabe-online.de/tenderdetails.html?id=852351"
    },
    {
        "title": "11-0498 Arnstadt, Prof.-Frosch-Str. 46a - Instandsetzung Laubeng\u00e4nge und Fassade, Los 1 Ger\u00fcstbauarbeiten",
        "link": "https://www.evergabe-online.de/tenderdetails.html?id=852343"
    },
    {
        "title": "Sanierung ehemaliges Sportlerheim als Dorfgemeinschafthaus (DGH) in Gr\u00f6ben,Los 6: Maler und Bodenbelagsarbeiten",
        "link": "https://www.evergabe-online.de/tenderdetails.html?id=852130"
    },
    {
        "title": "Sanierung ehemaliges Sportlerheim als Dorfgemeinschafthaus (DGH) in Gr\u00f6ben,Los 5: Trockenbauarbeiten",
        "link": "https://www.evergabe-online.de/tenderdetails.html?id=852127"
    },
    {
        "title": "Sanierung ehemaliges Sportlerheim als Dorfgemeinschafthaus (DGH) in Gr\u00f6ben,Los 4: Fassade, D\u00e4mmung, Aussenputzarbeiten",
        "link": "https://www.evergabe-online.de/tenderdetails.html?id=852121"
    },
    {
        "title": "Umr\u00fcstung Bender-System Haus 60a, 60b und ITS - Elektroarbeiten",
        "link": "https://www.evergabe-online.de/tenderdetails.html?id=852357"
    },
    {
        "title": "Ausbau des Stichkanals nach Salzgitter, Technische Erkundung Kampfmittelr\u00e4umung VH Wedtlenstedt",
        "link": "https://www.evergabe-online.de/tenderdetails.html?id=852380"
    },
    {
        "title": "e-Learning / Schulungssoftware",
        "link": "https://www.evergabe-online.de/tenderdetails.html?id=852371"
    }
]