[
    {
        "title": "Neubau Geh- und Radweg Laucha - Kirchscheidungen; Stra\u00dfenbauarbeiten",
        "link": "https://www.evergabe-online.de/tenderdetails.html?id=864754"
    },
    {
        "title": "Wartung von Sicherheitsbeleuchtungen in Sigmaringen - VOEK 281-26",
        "link": "https://www.evergabe-online.de/tenderdetails.html?id=865021"
    },
    {
        "title": "Feuerwehreinsatzfahrzeug Ger\u00e4tewagen Logistik (GW-L1)",
        "link": "https://www.evergabe-online.de/tenderdetails.html?id=865092"
    },
    {
        "title": "Pausen-Erinnerungs-Tool",
        "link": "https://www.evergabe-online.de/tenderdetails.html?id=865074"
    },
    {
        "title": "RTK/GNSS-System",
        "link": "https://www.evergabe-online.de/tenderdetails.html?id=865076"
    },
    {
        "title": "Inventarermittlung der F-Gase 2025/2026 - Daten fluorierter Treibhausgase in ausgew\u00e4hlten Quellgruppen f\u00fcr die nationale Emissionsberichterstattung gem\u00e4\u00df Klimarahmenkonvention f\u00fcr 2025 und 2026",
        "link": "https://www.evergabe-online.de/tenderdetails.html?id=863466"
    },
    {
        "title": "Sharegate Desktop Lizenzen (Migration Tool)",
        "link": "https://www.evergabe-online.de/tenderdetails.html?id=865025"
    },
    {
        "title": "Sanierung Regionales F\u00f6rderzentrum Pestalozzischule Schulteil 1 - Fliesenarbeiten",
        "link": "https://www.evergabe-online.de/tenderdetails.html?id=864071"
    },
    {
        "title": "Sanierung Regionales F\u00f6rderzentrum Pestalozzischule Schulteil 1 - Trockenbauarbeiten",
        "link": "https://www.evergabe-online.de/tenderdetails.html?id=864069"
    },
    {
        "title": "Elektroinstallationen",
        "link": "https://www.evergabe-online.de/tenderdetails.html?id=864929"
    }
]