[
    {
        "title": "Erhebungsdurchf\u00fchrung einer telefonischen Bev\u00f6lkerungsbefragung (CATI) im Rahmen der Studie \u201eDiskriminierungserfahrungen in Deutschland 2025\u201c",
        "link": "https://www.evergabe-online.de/tenderdetails.html?id=815736"
    },
    {
        "title": "REZ SW 45Unt2mV JC Wetterau",
        "link": "https://www.evergabe-online.de/tenderdetails.html?id=815726"
    },
    {
        "title": "REZ SW 16e_i JC BAd Kreuznach",
        "link": "https://www.evergabe-online.de/tenderdetails.html?id=815725"
    },
    {
        "title": "Industrie-PCs",
        "link": "https://www.evergabe-online.de/tenderdetails.html?id=815705"
    },
    {
        "title": "Staatsbibliothek zu Berlin - Transport- & Umzugsleistungen v. Kulturgut - Vergabe 2768/2025",
        "link": "https://www.evergabe-online.de/tenderdetails.html?id=815423"
    },
    {
        "title": "PB447 - Allradschlepper mit Frontlader",
        "link": "https://www.evergabe-online.de/tenderdetails.html?id=815422"
    },
    {
        "title": "Erneuerung der EL/WL-Anlage im Bereich der Leitzentrale Neuses",
        "link": "https://www.evergabe-online.de/tenderdetails.html?id=815257"
    },
    {
        "title": "TGS 10 und F\u00d6Z 5 - Heizung, Sanit\u00e4r, L\u00fcftung und Klimatisierung",
        "link": "https://www.evergabe-online.de/tenderdetails.html?id=815122"
    },
    {
        "title": "Los 406 BMA, EMA, Video, BOS, Perimeter - Erweiterungsbau Graphische Sammlungen",
        "link": "https://www.evergabe-online.de/tenderdetails.html?id=815038"
    },
    {
        "title": "Kohlenstoffinventur 2027",
        "link": "https://www.evergabe-online.de/tenderdetails.html?id=815391"
    }
]