[
    {
        "title": "Schlosserarbeiten",
        "link": "https://www.evergabe-online.de/tenderdetails.html?id=862638"
    },
    {
        "title": "Malerarbeiten und Innenputz",
        "link": "https://www.evergabe-online.de/tenderdetails.html?id=862634"
    },
    {
        "title": "Tischlerarbeiten",
        "link": "https://www.evergabe-online.de/tenderdetails.html?id=862628"
    },
    {
        "title": "L79 Eilenstedt - Haus Nienburg",
        "link": "https://www.evergabe-online.de/tenderdetails.html?id=862627"
    },
    {
        "title": "Gardelegen_LED Umstellung _Wohngebiet Schl\u00fcsselkorb",
        "link": "https://www.evergabe-online.de/tenderdetails.html?id=862624"
    },
    {
        "title": "Bek\u00e4mpfung des Eichenprozessionsspinners im Gebiet der Hansestadt Gardelegen Los mechanische Bek\u00e4mpfung",
        "link": "https://www.evergabe-online.de/tenderdetails.html?id=862623"
    },
    {
        "title": "Trockenbauarbeiten",
        "link": "https://www.evergabe-online.de/tenderdetails.html?id=862615"
    },
    {
        "title": "Transport & Verwertung/Entsorgung von stark kontaminiertem Schlamm aus einer WBA",
        "link": "https://www.evergabe-online.de/tenderdetails.html?id=862606"
    },
    {
        "title": "Neubau Feuerwehrger\u00e4tehaus Immekath Estricharbeiten",
        "link": "https://www.evergabe-online.de/tenderdetails.html?id=862612"
    },
    {
        "title": "Ger\u00fcstbauarbeiten und Fassade",
        "link": "https://www.evergabe-online.de/tenderdetails.html?id=862609"
    }
]