[
    {
        "title": "Bodenbelagsarbeiten",
        "link": "https://www.evergabe-online.de/tenderdetails.html?id=788083"
    },
    {
        "title": "Stadtnatur international - Vernetzungstreffen",
        "link": "https://www.evergabe-online.de/tenderdetails.html?id=788074"
    },
    {
        "title": "Streuobstwiese B\u00f6senrode",
        "link": "https://www.evergabe-online.de/tenderdetails.html?id=788071"
    },
    {
        "title": "REZ SW 45ind JC Neuwied",
        "link": "https://www.evergabe-online.de/tenderdetails.html?id=788062"
    },
    {
        "title": "Verkehrssicherung VKZ Travem\u00fcnde",
        "link": "https://www.evergabe-online.de/tenderdetails.html?id=787258"
    },
    {
        "title": "Ersatzneubau der C\u00e4cilienbr\u00fccke in Oldenburg Reinigungsarbeiten / Winterdienst Behelfsbr\u00fccke",
        "link": "https://www.evergabe-online.de/tenderdetails.html?id=787807"
    },
    {
        "title": "Arche Nebra, An der Steinkl\u00f6be 16, 06642 Nebra (Unstrut), Neubau einer raumlufttechnischen Anlage, Los 6.1: Raumlufttechnik",
        "link": "https://www.evergabe-online.de/tenderdetails.html?id=788046"
    },
    {
        "title": "Saarbr\u00fccken, Hafenstra\u00dfe 18, F\u00f6rdertechnik",
        "link": "https://www.evergabe-online.de/tenderdetails.html?id=788048"
    },
    {
        "title": "Kurierdienstleistung im Bezirk des Internen Service Dresden",
        "link": "https://www.evergabe-online.de/tenderdetails.html?id=787782"
    },
    {
        "title": "1/DLII4/PV454 - Ger\u00e4tetr\u00e4ger mit Anbauteilen",
        "link": "https://www.evergabe-online.de/tenderdetails.html?id=787814"
    }
]